{
    "title":  "Good life",
    "coverImage":  "https://pub-1208463a3c774431bf7e0ddcbd3cf670.r2.dev/cardsfolder/03.png",
    "items":  [
                  {
                      "imagem":  "https://pub-1208463a3c774431bf7e0ddcbd3cf670.r2.dev/Niveis/012/001/000001.webp",
                      "nomePortugues":  "eu comprei um livro",
                      "nomeIngles":  "I bought a book",
                      "categoria":  "FlashCard",
                      "audio":  "https://pub-1208463a3c774431bf7e0ddcbd3cf670.r2.dev/Niveis/012/001/000002.mp3",
                      "tense":  "present-simple",
                      "sentenceForm":  "affirmative"
                  },
                  {
                      "imagem":  "https://pub-1208463a3c774431bf7e0ddcbd3cf670.r2.dev/Niveis/012/001/000003.webp",
                      "nomePortugues":  "eu comi um sanduíche",
                      "nomeIngles":  "I ate a sandwich",
                      "categoria":  "FlashCard",
                      "audio":  "https://pub-1208463a3c774431bf7e0ddcbd3cf670.r2.dev/Niveis/012/001/000004.mp3",
                      "tense":  "present-simple",
                      "sentenceForm":  "affirmative"
                  },
                  {
                      "imagem":  "https://pub-1208463a3c774431bf7e0ddcbd3cf670.r2.dev/Niveis/012/001/000005.webp",
                      "nomePortugues":  "eu bebi suco",
                      "nomeIngles":  "I drank juice",
                      "categoria":  "FlashCard",
                      "audio":  "https://pub-1208463a3c774431bf7e0ddcbd3cf670.r2.dev/Niveis/012/001/000006.mp3",
                      "tense":  "present-simple",
                      "sentenceForm":  "affirmative"
                  },
                  {
                      "imagem":  "https://pub-1208463a3c774431bf7e0ddcbd3cf670.r2.dev/Niveis/012/001/000007.webp",
                      "nomePortugues":  "eu cortei pão",
                      "nomeIngles":  "I cut bread",
                      "categoria":  "FlashCard",
                      "audio":  "https://pub-1208463a3c774431bf7e0ddcbd3cf670.r2.dev/Niveis/012/001/000008.mp3",
                      "tense":  "present-simple",
                      "sentenceForm":  "affirmative"
                  },
                  {
                      "imagem":  "https://pub-1208463a3c774431bf7e0ddcbd3cf670.r2.dev/Niveis/012/001/000009.webp",
                      "nomePortugues":  "eu liguei a luz",
                      "nomeIngles":  "I turned on the light",
                      "categoria":  "FlashCard",
                      "audio":  "https://pub-1208463a3c774431bf7e0ddcbd3cf670.r2.dev/Niveis/012/001/000010.mp3",
                      "tense":  "present-simple",
                      "sentenceForm":  "affirmative"
                  },
                  {
                      "imagem":  "https://pub-1208463a3c774431bf7e0ddcbd3cf670.r2.dev/Niveis/012/001/000011.webp",
                      "nomePortugues":  "eu desliguei a TV",
                      "nomeIngles":  "I turned off the TV",
                      "categoria":  "FlashCard",
                      "audio":  "https://pub-1208463a3c774431bf7e0ddcbd3cf670.r2.dev/Niveis/012/001/000012.mp3",
                      "tense":  "present-simple",
                      "sentenceForm":  "affirmative"
                  },
                  {
                      "imagem":  "https://pub-1208463a3c774431bf7e0ddcbd3cf670.r2.dev/Niveis/012/001/000013.webp",
                      "nomePortugues":  "eu lavei as mãos",
                      "nomeIngles":  "I washed my hands",
                      "categoria":  "FlashCard",
                      "audio":  "https://pub-1208463a3c774431bf7e0ddcbd3cf670.r2.dev/Niveis/012/001/000014.mp3",
                      "tense":  "present-simple",
                      "sentenceForm":  "affirmative"
                  },
                  {
                      "imagem":  "https://pub-1208463a3c774431bf7e0ddcbd3cf670.r2.dev/Niveis/012/001/000015.webp",
                      "nomePortugues":  "eu arrumei a cama",
                      "nomeIngles":  "I made the bed",
                      "categoria":  "FlashCard",
                      "audio":  "https://pub-1208463a3c774431bf7e0ddcbd3cf670.r2.dev/Niveis/012/001/000016.mp3",
                      "tense":  "present-simple",
                      "sentenceForm":  "affirmative"
                  },
                  {
                      "imagem":  "https://pub-1208463a3c774431bf7e0ddcbd3cf670.r2.dev/Niveis/012/001/000017.webp",
                      "nomePortugues":  "eu limpei o chão",
                      "nomeIngles":  "I cleaned the floor",
                      "categoria":  "FlashCard",
                      "audio":  "https://pub-1208463a3c774431bf7e0ddcbd3cf670.r2.dev/Niveis/012/001/000018.mp3",
                      "tense":  "present-simple",
                      "sentenceForm":  "affirmative"
                  },
                  {
                      "imagem":  "https://pub-1208463a3c774431bf7e0ddcbd3cf670.r2.dev/Niveis/012/001/000019.webp",
                      "nomePortugues":  "eu abri o portão",
                      "nomeIngles":  "I opened the gate",
                      "categoria":  "FlashCard",
                      "audio":  "https://pub-1208463a3c774431bf7e0ddcbd3cf670.r2.dev/Niveis/012/001/000020.mp3",
                      "tense":  "present-simple",
                      "sentenceForm":  "affirmative"
                  },
                  {
                      "imagem":  "https://pub-1208463a3c774431bf7e0ddcbd3cf670.r2.dev/Niveis/012/001/000021.webp",
                      "nomePortugues":  "eu fechei a loja",
                      "nomeIngles":  "I closed the store",
                      "categoria":  "FlashCard",
                      "audio":  "https://pub-1208463a3c774431bf7e0ddcbd3cf670.r2.dev/Niveis/012/001/000022.mp3",
                      "tense":  "present-simple",
                      "sentenceForm":  "affirmative"
                  },
                  {
                      "imagem":  "https://pub-1208463a3c774431bf7e0ddcbd3cf670.r2.dev/Niveis/012/001/000023.webp",
                      "nomePortugues":  "eu visitei um amigo",
                      "nomeIngles":  "I visited a friend",
                      "categoria":  "FlashCard",
                      "audio":  "https://pub-1208463a3c774431bf7e0ddcbd3cf670.r2.dev/Niveis/012/001/000024.mp3",
                      "tense":  "present-simple",
                      "sentenceForm":  "affirmative"
                  },
                  {
                      "imagem":  "https://pub-1208463a3c774431bf7e0ddcbd3cf670.r2.dev/Niveis/012/001/000025.webp",
                      "nomePortugues":  "eu encontrei minha chave",
                      "nomeIngles":  "I found my key",
                      "categoria":  "FlashCard",
                      "audio":  "https://pub-1208463a3c774431bf7e0ddcbd3cf670.r2.dev/Niveis/012/001/000026.mp3",
                      "tense":  "present-simple",
                      "sentenceForm":  "affirmative"
                  },
                  {
                      "imagem":  "https://pub-1208463a3c774431bf7e0ddcbd3cf670.r2.dev/Niveis/012/001/000027.webp",
                      "nomePortugues":  "eu perdi meu celular",
                      "nomeIngles":  "I lost my phone",
                      "categoria":  "FlashCard",
                      "audio":  "https://pub-1208463a3c774431bf7e0ddcbd3cf670.r2.dev/Niveis/012/001/000028.mp3",
                      "tense":  "present-simple",
                      "sentenceForm":  "affirmative"
                  },
                  {
                      "imagem":  "https://pub-1208463a3c774431bf7e0ddcbd3cf670.r2.dev/Niveis/012/001/000029.webp",
                      "nomePortugues":  "eu comprei uma camisa",
                      "nomeIngles":  "I bought a shirt",
                      "categoria":  "FlashCard",
                      "audio":  "https://pub-1208463a3c774431bf7e0ddcbd3cf670.r2.dev/Niveis/012/001/000030.mp3",
                      "tense":  "present-simple",
                      "sentenceForm":  "affirmative"
                  },
                  {
                      "imagem":  "https://pub-1208463a3c774431bf7e0ddcbd3cf670.r2.dev/Niveis/012/001/000031.webp",
                      "nomePortugues":  "eu usei um computador",
                      "nomeIngles":  "I used a computer",
                      "categoria":  "FlashCard",
                      "audio":  "https://pub-1208463a3c774431bf7e0ddcbd3cf670.r2.dev/Niveis/012/001/000032.mp3",
                      "tense":  "present-simple",
                      "sentenceForm":  "affirmative"
                  },
                  {
                      "imagem":  "https://pub-1208463a3c774431bf7e0ddcbd3cf670.r2.dev/Niveis/012/001/000033.webp",
                      "nomePortugues":  "eu mandei uma mensagem",
                      "nomeIngles":  "I sent a message",
                      "categoria":  "FlashCard",
                      "audio":  "https://pub-1208463a3c774431bf7e0ddcbd3cf670.r2.dev/Niveis/012/001/000034.mp3",
                      "tense":  "present-simple",
                      "sentenceForm":  "affirmative"
                  },
                  {
                      "imagem":  "https://pub-1208463a3c774431bf7e0ddcbd3cf670.r2.dev/Niveis/012/001/000035.webp",
                      "nomePortugues":  "eu recebi um presente",
                      "nomeIngles":  "I received a gift",
                      "categoria":  "FlashCard",
                      "audio":  "https://pub-1208463a3c774431bf7e0ddcbd3cf670.r2.dev/Niveis/012/001/000036.mp3",
                      "tense":  "present-simple",
                      "sentenceForm":  "affirmative"
                  },
                  {
                      "imagem":  "https://pub-1208463a3c774431bf7e0ddcbd3cf670.r2.dev/Niveis/012/001/000037.webp",
                      "nomePortugues":  "eu fiz café",
                      "nomeIngles":  "I made coffee",
                      "categoria":  "FlashCard",
                      "audio":  "https://pub-1208463a3c774431bf7e0ddcbd3cf670.r2.dev/Niveis/012/001/000038.mp3",
                      "tense":  "present-simple",
                      "sentenceForm":  "affirmative"
                  },
                  {
                      "imagem":  "https://pub-1208463a3c774431bf7e0ddcbd3cf670.r2.dev/Niveis/012/001/000039.webp",
                      "nomePortugues":  "eu preparei o jantar",
                      "nomeIngles":  "I prepared dinner",
                      "categoria":  "FlashCard",
                      "audio":  "https://pub-1208463a3c774431bf7e0ddcbd3cf670.r2.dev/Niveis/012/001/000040.mp3",
                      "tense":  "present-simple",
                      "sentenceForm":  "affirmative"
                  },
                  {
                      "imagem":  "https://pub-1208463a3c774431bf7e0ddcbd3cf670.r2.dev/Niveis/012/001/000041.webp",
                      "nomePortugues":  "eu acendi uma vela",
                      "nomeIngles":  "I lit a candle",
                      "categoria":  "FlashCard",
                      "audio":  "https://pub-1208463a3c774431bf7e0ddcbd3cf670.r2.dev/Niveis/012/001/000042.mp3",
                      "tense":  "present-simple",
                      "sentenceForm":  "affirmative"
                  },
                  {
                      "imagem":  "https://pub-1208463a3c774431bf7e0ddcbd3cf670.r2.dev/Niveis/012/001/000043.webp",
                      "nomePortugues":  "eu apaguei a luz",
                      "nomeIngles":  "I turned off the light",
                      "categoria":  "FlashCard",
                      "audio":  "https://pub-1208463a3c774431bf7e0ddcbd3cf670.r2.dev/Niveis/012/001/000044.mp3",
                      "tense":  "present-simple",
                      "sentenceForm":  "affirmative"
                  },
                  {
                      "imagem":  "https://pub-1208463a3c774431bf7e0ddcbd3cf670.r2.dev/Niveis/012/001/000045.webp",
                      "nomePortugues":  "eu caminhei na rua",
                      "nomeIngles":  "I walked on the street",
                      "categoria":  "FlashCard",
                      "audio":  "https://pub-1208463a3c774431bf7e0ddcbd3cf670.r2.dev/Niveis/012/001/000046.mp3",
                      "tense":  "present-simple",
                      "sentenceForm":  "affirmative"
                  },
                  {
                      "imagem":  "https://pub-1208463a3c774431bf7e0ddcbd3cf670.r2.dev/Niveis/012/001/000047.webp",
                      "nomePortugues":  "eu corri no parque",
                      "nomeIngles":  "I ran in the park",
                      "categoria":  "FlashCard",
                      "audio":  "https://pub-1208463a3c774431bf7e0ddcbd3cf670.r2.dev/Niveis/012/001/000048.mp3",
                      "tense":  "present-simple",
                      "sentenceForm":  "affirmative"
                  },
                  {
                      "imagem":  "https://pub-1208463a3c774431bf7e0ddcbd3cf670.r2.dev/Niveis/012/001/000049.webp",
                      "nomePortugues":  "eu sentei na cadeira",
                      "nomeIngles":  "I sat on the chair",
                      "categoria":  "FlashCard",
                      "audio":  "https://pub-1208463a3c774431bf7e0ddcbd3cf670.r2.dev/Niveis/012/001/000050.mp3",
                      "tense":  "present-simple",
                      "sentenceForm":  "affirmative"
                  },
                  {
                      "imagem":  "https://pub-1208463a3c774431bf7e0ddcbd3cf670.r2.dev/Niveis/012/001/000051.webp",
                      "nomePortugues":  "eu levantei cedo",
                      "nomeIngles":  "I woke up early",
                      "categoria":  "FlashCard",
                      "audio":  "https://pub-1208463a3c774431bf7e0ddcbd3cf670.r2.dev/Niveis/012/001/000052.mp3",
                      "tense":  "present-simple",
                      "sentenceForm":  "affirmative"
                  },
                  {
                      "imagem":  "https://pub-1208463a3c774431bf7e0ddcbd3cf670.r2.dev/Niveis/012/001/000053.webp",
                      "nomePortugues":  "eu dormi tarde",
                      "nomeIngles":  "I slept late",
                      "categoria":  "FlashCard",
                      "audio":  "https://pub-1208463a3c774431bf7e0ddcbd3cf670.r2.dev/Niveis/012/001/000054.mp3",
                      "tense":  "present-simple",
                      "sentenceForm":  "affirmative"
                  },
                  {
                      "imagem":  "https://pub-1208463a3c774431bf7e0ddcbd3cf670.r2.dev/Niveis/012/001/000055.webp",
                      "nomePortugues":  "eu ouvi um barulho",
                      "nomeIngles":  "I heard a noise",
                      "categoria":  "FlashCard",
                      "audio":  "https://pub-1208463a3c774431bf7e0ddcbd3cf670.r2.dev/Niveis/012/001/000056.mp3",
                      "tense":  "present-simple",
                      "sentenceForm":  "affirmative"
                  },
                  {
                      "imagem":  "https://pub-1208463a3c774431bf7e0ddcbd3cf670.r2.dev/Niveis/012/001/000057.webp",
                      "nomePortugues":  "eu vi um pássaro",
                      "nomeIngles":  "I saw a bird",
                      "categoria":  "FlashCard",
                      "audio":  "https://pub-1208463a3c774431bf7e0ddcbd3cf670.r2.dev/Niveis/012/001/000058.mp3",
                      "tense":  "present-simple",
                      "sentenceForm":  "affirmative"
                  },
                  {
                      "imagem":  "https://pub-1208463a3c774431bf7e0ddcbd3cf670.r2.dev/Niveis/012/001/000059.webp",
                      "nomePortugues":  "eu tirei meu sapato",
                      "nomeIngles":  "I took off my shoe",
                      "categoria":  "FlashCard",
                      "audio":  "https://pub-1208463a3c774431bf7e0ddcbd3cf670.r2.dev/Niveis/012/001/000060.mp3",
                      "tense":  "present-simple",
                      "sentenceForm":  "affirmative"
                  }
              ]
}
