{
  "title": "Transporte",
  "coverImage": "https://pub-1208463a3c774431bf7e0ddcbd3cf670.r2.dev/cardsfolder/Sequ%C3%AAncia%2001.00_00_00_00.Quadro001.png",
  "items": [
    {
      "imagem": "https://pub-1208463a3c774431bf7e0ddcbd3cf670.r2.dev/Niveis/118/001/000001.webp",
      "nomePortugues": "Carro",
      "nomeIngles": "Car",
      "categoria": "PlayTalk",
      "audio": "https://pub-1208463a3c774431bf7e0ddcbd3cf670.r2.dev/Niveis/118/001/000002.mp3",
      "tense": "present-simple",
      "sentenceForm": "affirmative"
    },
    {
      "imagem": "https://pub-1208463a3c774431bf7e0ddcbd3cf670.r2.dev/Niveis/118/001/000003.webp",
      "nomePortugues": "Carro esportivo",
      "nomeIngles": "Sports car",
      "categoria": "PlayTalk",
      "audio": "https://pub-1208463a3c774431bf7e0ddcbd3cf670.r2.dev/Niveis/118/001/000004.mp3",
      "tense": "present-simple",
      "sentenceForm": "affirmative"
    },
    {
      "imagem": "https://pub-1208463a3c774431bf7e0ddcbd3cf670.r2.dev/Niveis/118/001/000005.webp",
      "nomePortugues": "Carro elétrico",
      "nomeIngles": "Electric car",
      "categoria": "PlayTalk",
      "audio": "https://pub-1208463a3c774431bf7e0ddcbd3cf670.r2.dev/Niveis/118/001/000006.mp3",
      "tense": "present-simple",
      "sentenceForm": "affirmative"
    },
    {
      "imagem": "https://pub-1208463a3c774431bf7e0ddcbd3cf670.r2.dev/Niveis/118/001/000007.webp",
      "nomePortugues": "Carro híbrido",
      "nomeIngles": "Hybrid car",
      "categoria": "PlayTalk",
      "audio": "https://pub-1208463a3c774431bf7e0ddcbd3cf670.r2.dev/Niveis/118/001/000008.mp3",
      "tense": "present-simple",
      "sentenceForm": "affirmative"
    },
    {
      "imagem": "https://pub-1208463a3c774431bf7e0ddcbd3cf670.r2.dev/Niveis/118/001/000009.webp",
      "nomePortugues": "Carro de corrida",
      "nomeIngles": "Race car",
      "categoria": "PlayTalk",
      "audio": "https://pub-1208463a3c774431bf7e0ddcbd3cf670.r2.dev/Niveis/118/001/000010.mp3",
      "tense": "present-simple",
      "sentenceForm": "affirmative"
    },
    {
      "imagem": "https://pub-1208463a3c774431bf7e0ddcbd3cf670.r2.dev/Niveis/118/001/000011.webp",
      "nomePortugues": "Carro de polícia",
      "nomeIngles": "Police car",
      "categoria": "PlayTalk",
      "audio": "https://pub-1208463a3c774431bf7e0ddcbd3cf670.r2.dev/Niveis/118/001/000012.mp3",
      "tense": "present-simple",
      "sentenceForm": "affirmative"
    },
    {
      "imagem": "https://pub-1208463a3c774431bf7e0ddcbd3cf670.r2.dev/Niveis/118/001/000013.webp",
      "nomePortugues": "Táxi",
      "nomeIngles": "Taxi",
      "categoria": "PlayTalk",
      "audio": "https://pub-1208463a3c774431bf7e0ddcbd3cf670.r2.dev/Niveis/118/001/000014.mp3",
      "tense": "present-simple",
      "sentenceForm": "affirmative"
    },
    {
      "imagem": "https://pub-1208463a3c774431bf7e0ddcbd3cf670.r2.dev/Niveis/118/001/000015.webp",
      "nomePortugues": "Uber",
      "nomeIngles": "Uber",
      "categoria": "PlayTalk",
      "audio": "https://pub-1208463a3c774431bf7e0ddcbd3cf670.r2.dev/Niveis/118/001/000016.mp3",
      "tense": "present-simple",
      "sentenceForm": "affirmative"
    },
    {
      "imagem": "https://pub-1208463a3c774431bf7e0ddcbd3cf670.r2.dev/Niveis/118/001/000017.webp",
      "nomePortugues": "Ônibus",
      "nomeIngles": "Bus",
      "categoria": "PlayTalk",
      "audio": "https://pub-1208463a3c774431bf7e0ddcbd3cf670.r2.dev/Niveis/118/001/000018.mp3",
      "tense": "present-simple",
      "sentenceForm": "affirmative"
    },
    {
      "imagem": "https://pub-1208463a3c774431bf7e0ddcbd3cf670.r2.dev/Niveis/118/001/000019.webp",
      "nomePortugues": "Ônibus escolar",
      "nomeIngles": "School bus",
      "categoria": "PlayTalk",
      "audio": "https://pub-1208463a3c774431bf7e0ddcbd3cf670.r2.dev/Niveis/118/001/000020.mp3",
      "tense": "present-simple",
      "sentenceForm": "affirmative"
    },
    {
      "imagem": "https://pub-1208463a3c774431bf7e0ddcbd3cf670.r2.dev/Niveis/118/001/000021.webp",
      "nomePortugues": "Micro-ônibus",
      "nomeIngles": "Minibus",
      "categoria": "PlayTalk",
      "audio": "https://pub-1208463a3c774431bf7e0ddcbd3cf670.r2.dev/Niveis/118/001/000022.mp3",
      "tense": "present-simple",
      "sentenceForm": "affirmative"
    },
    {
      "imagem": "https://pub-1208463a3c774431bf7e0ddcbd3cf670.r2.dev/Niveis/118/001/000023.webp",
      "nomePortugues": "Van",
      "nomeIngles": "Van",
      "categoria": "PlayTalk",
      "audio": "https://pub-1208463a3c774431bf7e0ddcbd3cf670.r2.dev/Niveis/118/001/000024.mp3",
      "tense": "present-simple",
      "sentenceForm": "affirmative"
    },
    {
      "imagem": "https://pub-1208463a3c774431bf7e0ddcbd3cf670.r2.dev/Niveis/118/001/000025.webp",
      "nomePortugues": "Van de carga",
      "nomeIngles": "Cargo van",
      "categoria": "PlayTalk",
      "audio": "https://pub-1208463a3c774431bf7e0ddcbd3cf670.r2.dev/Niveis/118/001/000026.mp3",
      "tense": "present-simple",
      "sentenceForm": "affirmative"
    },
    {
      "imagem": "https://pub-1208463a3c774431bf7e0ddcbd3cf670.r2.dev/Niveis/118/001/000027.webp",
      "nomePortugues": "Caminhão",
      "nomeIngles": "Truck",
      "categoria": "PlayTalk",
      "audio": "https://pub-1208463a3c774431bf7e0ddcbd3cf670.r2.dev/Niveis/118/001/000028.mp3",
      "tense": "present-simple",
      "sentenceForm": "affirmative"
    },
    {
      "imagem": "https://pub-1208463a3c774431bf7e0ddcbd3cf670.r2.dev/Niveis/118/001/000029.webp",
      "nomePortugues": "Caminhão pequeno",
      "nomeIngles": "Pickup truck",
      "categoria": "PlayTalk",
      "audio": "https://pub-1208463a3c774431bf7e0ddcbd3cf670.r2.dev/Niveis/118/001/000030.mp3",
      "tense": "present-simple",
      "sentenceForm": "affirmative"
    },
    {
      "imagem": "https://pub-1208463a3c774431bf7e0ddcbd3cf670.r2.dev/Niveis/118/001/000031.webp",
      "nomePortugues": "Caminhão de lixo",
      "nomeIngles": "Garbage truck",
      "categoria": "PlayTalk",
      "audio": "https://pub-1208463a3c774431bf7e0ddcbd3cf670.r2.dev/Niveis/118/001/000032.mp3",
      "tense": "present-simple",
      "sentenceForm": "affirmative"
    },
    {
      "imagem": "https://pub-1208463a3c774431bf7e0ddcbd3cf670.r2.dev/Niveis/118/001/000033.webp",
      "nomePortugues": "Caminhão de bombeiros",
      "nomeIngles": "Fire truck",
      "categoria": "PlayTalk",
      "audio": "https://pub-1208463a3c774431bf7e0ddcbd3cf670.r2.dev/Niveis/118/001/000034.mp3",
      "tense": "present-simple",
      "sentenceForm": "affirmative"
    },
    {
      "imagem": "https://pub-1208463a3c774431bf7e0ddcbd3cf670.r2.dev/Niveis/118/001/000035.webp",
      "nomePortugues": "Ambulância",
      "nomeIngles": "Ambulance",
      "categoria": "PlayTalk",
      "audio": "https://pub-1208463a3c774431bf7e0ddcbd3cf670.r2.dev/Niveis/118/001/000036.mp3",
      "tense": "present-simple",
      "sentenceForm": "affirmative"
    },
    {
      "imagem": "https://pub-1208463a3c774431bf7e0ddcbd3cf670.r2.dev/Niveis/118/001/000037.webp",
      "nomePortugues": "Moto",
      "nomeIngles": "Motorcycle",
      "categoria": "PlayTalk",
      "audio": "https://pub-1208463a3c774431bf7e0ddcbd3cf670.r2.dev/Niveis/118/001/000038.mp3",
      "tense": "present-simple",
      "sentenceForm": "affirmative"
    },
    {
      "imagem": "https://pub-1208463a3c774431bf7e0ddcbd3cf670.r2.dev/Niveis/118/001/000039.webp",
      "nomePortugues": "Moto esportiva",
      "nomeIngles": "Sport bike",
      "categoria": "PlayTalk",
      "audio": "https://pub-1208463a3c774431bf7e0ddcbd3cf670.r2.dev/Niveis/118/001/000040.mp3",
      "tense": "present-simple",
      "sentenceForm": "affirmative"
    },
    {
      "imagem": "https://pub-1208463a3c774431bf7e0ddcbd3cf670.r2.dev/Niveis/118/001/000041.webp",
      "nomePortugues": "Scooter",
      "nomeIngles": "Scooter",
      "categoria": "PlayTalk",
      "audio": "https://pub-1208463a3c774431bf7e0ddcbd3cf670.r2.dev/Niveis/118/001/000042.mp3",
      "tense": "present-simple",
      "sentenceForm": "affirmative"
    },
    {
      "imagem": "https://pub-1208463a3c774431bf7e0ddcbd3cf670.r2.dev/Niveis/118/001/000043.webp",
      "nomePortugues": "Bicicleta",
      "nomeIngles": "Bike",
      "categoria": "PlayTalk",
      "audio": "https://pub-1208463a3c774431bf7e0ddcbd3cf670.r2.dev/Niveis/118/001/000044.mp3",
      "tense": "present-simple",
      "sentenceForm": "affirmative"
    },
    {
      "imagem": "https://pub-1208463a3c774431bf7e0ddcbd3cf670.r2.dev/Niveis/118/001/000045.webp",
      "nomePortugues": "Bicicleta elétrica",
      "nomeIngles": "E-bike",
      "categoria": "PlayTalk",
      "audio": "https://pub-1208463a3c774431bf7e0ddcbd3cf670.r2.dev/Niveis/118/001/000046.mp3",
      "tense": "present-simple",
      "sentenceForm": "affirmative"
    },
    {
      "imagem": "https://pub-1208463a3c774431bf7e0ddcbd3cf670.r2.dev/Niveis/118/001/000047.webp",
      "nomePortugues": "Bicicleta de montanha",
      "nomeIngles": "Mountain bike",
      "categoria": "PlayTalk",
      "audio": "https://pub-1208463a3c774431bf7e0ddcbd3cf670.r2.dev/Niveis/118/001/000048.mp3",
      "tense": "present-simple",
      "sentenceForm": "affirmative"
    },
    {
      "imagem": "https://pub-1208463a3c774431bf7e0ddcbd3cf670.r2.dev/Niveis/118/001/000049.webp",
      "nomePortugues": "Bicicleta de corrida",
      "nomeIngles": "Road bike",
      "categoria": "PlayTalk",
      "audio": "https://pub-1208463a3c774431bf7e0ddcbd3cf670.r2.dev/Niveis/118/001/000050.mp3",
      "tense": "present-simple",
      "sentenceForm": "affirmative"
    },
    {
      "imagem": "https://pub-1208463a3c774431bf7e0ddcbd3cf670.r2.dev/Niveis/118/001/000051.webp",
      "nomePortugues": "Patinete",
      "nomeIngles": "Scooter",
      "categoria": "PlayTalk",
      "audio": "https://pub-1208463a3c774431bf7e0ddcbd3cf670.r2.dev/Niveis/118/001/000052.mp3",
      "tense": "present-simple",
      "sentenceForm": "affirmative"
    },
    {
      "imagem": "https://pub-1208463a3c774431bf7e0ddcbd3cf670.r2.dev/Niveis/118/001/000053.webp",
      "nomePortugues": "Patinete elétrico",
      "nomeIngles": "Electric scooter",
      "categoria": "PlayTalk",
      "audio": "https://pub-1208463a3c774431bf7e0ddcbd3cf670.r2.dev/Niveis/118/001/000054.mp3",
      "tense": "present-simple",
      "sentenceForm": "affirmative"
    },
    {
      "imagem": "https://pub-1208463a3c774431bf7e0ddcbd3cf670.r2.dev/Niveis/118/001/000055.webp",
      "nomePortugues": "Skate",
      "nomeIngles": "Skateboard",
      "categoria": "PlayTalk",
      "audio": "https://pub-1208463a3c774431bf7e0ddcbd3cf670.r2.dev/Niveis/118/001/000056.mp3",
      "tense": "present-simple",
      "sentenceForm": "affirmative"
    },
    {
      "imagem": "https://pub-1208463a3c774431bf7e0ddcbd3cf670.r2.dev/Niveis/118/001/000057.webp",
      "nomePortugues": "Trem",
      "nomeIngles": "Train",
      "categoria": "PlayTalk",
      "audio": "https://pub-1208463a3c774431bf7e0ddcbd3cf670.r2.dev/Niveis/118/001/000058.mp3",
      "tense": "present-simple",
      "sentenceForm": "affirmative"
    },
    {
      "imagem": "https://pub-1208463a3c774431bf7e0ddcbd3cf670.r2.dev/Niveis/118/001/000059.webp",
      "nomePortugues": "Metrô",
      "nomeIngles": "Subway",
      "categoria": "PlayTalk",
      "audio": "https://pub-1208463a3c774431bf7e0ddcbd3cf670.r2.dev/Niveis/118/001/000060.mp3",
      "tense": "present-simple",
      "sentenceForm": "affirmative"
    },
    {
      "imagem": "https://pub-1208463a3c774431bf7e0ddcbd3cf670.r2.dev/Niveis/118/001/000061.webp",
      "nomePortugues": "Bonde",
      "nomeIngles": "Tram",
      "categoria": "PlayTalk",
      "audio": "https://pub-1208463a3c774431bf7e0ddcbd3cf670.r2.dev/Niveis/118/001/000062.mp3",
      "tense": "present-simple",
      "sentenceForm": "affirmative"
    },
    {
      "imagem": "https://pub-1208463a3c774431bf7e0ddcbd3cf670.r2.dev/Niveis/118/001/000063.webp",
      "nomePortugues": "Trem de alta velocidade",
      "nomeIngles": "Bullet train",
      "categoria": "PlayTalk",
      "audio": "https://pub-1208463a3c774431bf7e0ddcbd3cf670.r2.dev/Niveis/118/001/000064.mp3",
      "tense": "present-simple",
      "sentenceForm": "affirmative"
    },
    {
      "imagem": "https://pub-1208463a3c774431bf7e0ddcbd3cf670.r2.dev/Niveis/118/001/000065.webp",
      "nomePortugues": "Avião",
      "nomeIngles": "Airplane",
      "categoria": "PlayTalk",
      "audio": "https://pub-1208463a3c774431bf7e0ddcbd3cf670.r2.dev/Niveis/118/001/000066.mp3",
      "tense": "present-simple",
      "sentenceForm": "affirmative"
    },
    {
      "imagem": "https://pub-1208463a3c774431bf7e0ddcbd3cf670.r2.dev/Niveis/118/001/000067.webp",
      "nomePortugues": "Jato",
      "nomeIngles": "Jet",
      "categoria": "PlayTalk",
      "audio": "https://pub-1208463a3c774431bf7e0ddcbd3cf670.r2.dev/Niveis/118/001/000068.mp3",
      "tense": "present-simple",
      "sentenceForm": "affirmative"
    },
    {
      "imagem": "https://pub-1208463a3c774431bf7e0ddcbd3cf670.r2.dev/Niveis/118/001/000069.webp",
      "nomePortugues": "Helicóptero",
      "nomeIngles": "Helicopter",
      "categoria": "PlayTalk",
      "audio": "https://pub-1208463a3c774431bf7e0ddcbd3cf670.r2.dev/Niveis/118/001/000070.mp3",
      "tense": "present-simple",
      "sentenceForm": "affirmative"
    },
    {
      "imagem": "https://pub-1208463a3c774431bf7e0ddcbd3cf670.r2.dev/Niveis/118/001/000071.webp",
      "nomePortugues": "Foguete",
      "nomeIngles": "Rocket",
      "categoria": "PlayTalk",
      "audio": "https://pub-1208463a3c774431bf7e0ddcbd3cf670.r2.dev/Niveis/118/001/000072.mp3",
      "tense": "present-simple",
      "sentenceForm": "affirmative"
    },
    {
      "imagem": "https://pub-1208463a3c774431bf7e0ddcbd3cf670.r2.dev/Niveis/118/001/000073.webp",
      "nomePortugues": "Barco",
      "nomeIngles": "Boat",
      "categoria": "PlayTalk",
      "audio": "https://pub-1208463a3c774431bf7e0ddcbd3cf670.r2.dev/Niveis/118/001/000074.mp3",
      "tense": "present-simple",
      "sentenceForm": "affirmative"
    },
    {
      "imagem": "https://pub-1208463a3c774431bf7e0ddcbd3cf670.r2.dev/Niveis/118/001/000075.webp",
      "nomePortugues": "Lancha",
      "nomeIngles": "Speedboat",
      "categoria": "PlayTalk",
      "audio": "https://pub-1208463a3c774431bf7e0ddcbd3cf670.r2.dev/Niveis/118/001/000076.mp3",
      "tense": "present-simple",
      "sentenceForm": "affirmative"
    },
    {
      "imagem": "https://pub-1208463a3c774431bf7e0ddcbd3cf670.r2.dev/Niveis/118/001/000077.webp",
      "nomePortugues": "Navio",
      "nomeIngles": "Ship",
      "categoria": "PlayTalk",
      "audio": "https://pub-1208463a3c774431bf7e0ddcbd3cf670.r2.dev/Niveis/118/001/000078.mp3",
      "tense": "present-simple",
      "sentenceForm": "affirmative"
    },
    {
      "imagem": "https://pub-1208463a3c774431bf7e0ddcbd3cf670.r2.dev/Niveis/118/001/000079.webp",
      "nomePortugues": "Navio de cruzeiro",
      "nomeIngles": "Cruise ship",
      "categoria": "PlayTalk",
      "audio": "https://pub-1208463a3c774431bf7e0ddcbd3cf670.r2.dev/Niveis/118/001/000080.mp3",
      "tense": "present-simple",
      "sentenceForm": "affirmative"
    },
    {
      "imagem": "https://pub-1208463a3c774431bf7e0ddcbd3cf670.r2.dev/Niveis/118/001/000081.webp",
      "nomePortugues": "Submarino",
      "nomeIngles": "Submarine",
      "categoria": "PlayTalk",
      "audio": "https://pub-1208463a3c774431bf7e0ddcbd3cf670.r2.dev/Niveis/118/001/000082.mp3",
      "tense": "present-simple",
      "sentenceForm": "affirmative"
    },
    {
      "imagem": "https://pub-1208463a3c774431bf7e0ddcbd3cf670.r2.dev/Niveis/118/001/000083.webp",
      "nomePortugues": "Jet ski",
      "nomeIngles": "Jet ski",
      "categoria": "PlayTalk",
      "audio": "https://pub-1208463a3c774431bf7e0ddcbd3cf670.r2.dev/Niveis/118/001/000084.mp3",
      "tense": "present-simple",
      "sentenceForm": "affirmative"
    },
    {
      "imagem": "https://pub-1208463a3c774431bf7e0ddcbd3cf670.r2.dev/Niveis/118/001/000085.webp",
      "nomePortugues": "Balsa",
      "nomeIngles": "Ferry",
      "categoria": "PlayTalk",
      "audio": "https://pub-1208463a3c774431bf7e0ddcbd3cf670.r2.dev/Niveis/118/001/000086.mp3",
      "tense": "present-simple",
      "sentenceForm": "affirmative"
    },
    {
      "imagem": "https://pub-1208463a3c774431bf7e0ddcbd3cf670.r2.dev/Niveis/118/001/000087.webp",
      "nomePortugues": "Trator",
      "nomeIngles": "Tractor",
      "categoria": "PlayTalk",
      "audio": "https://pub-1208463a3c774431bf7e0ddcbd3cf670.r2.dev/Niveis/118/001/000088.mp3",
      "tense": "present-simple",
      "sentenceForm": "affirmative"
    },
    {
      "imagem": "https://pub-1208463a3c774431bf7e0ddcbd3cf670.r2.dev/Niveis/118/001/000089.webp",
      "nomePortugues": "Escavadeira",
      "nomeIngles": "Excavator",
      "categoria": "PlayTalk",
      "audio": "https://pub-1208463a3c774431bf7e0ddcbd3cf670.r2.dev/Niveis/118/001/000090.mp3",
      "tense": "present-simple",
      "sentenceForm": "affirmative"
    },
    {
      "imagem": "https://pub-1208463a3c774431bf7e0ddcbd3cf670.r2.dev/Niveis/118/001/000091.webp",
      "nomePortugues": "Guindaste",
      "nomeIngles": "Crane",
      "categoria": "PlayTalk",
      "audio": "https://pub-1208463a3c774431bf7e0ddcbd3cf670.r2.dev/Niveis/118/001/000092.mp3",
      "tense": "present-simple",
      "sentenceForm": "affirmative"
    },
    {
      "imagem": "https://pub-1208463a3c774431bf7e0ddcbd3cf670.r2.dev/Niveis/118/001/000093.webp",
      "nomePortugues": "Carrinho de golfe",
      "nomeIngles": "Golf cart",
      "categoria": "PlayTalk",
      "audio": "https://pub-1208463a3c774431bf7e0ddcbd3cf670.r2.dev/Niveis/118/001/000094.mp3",
      "tense": "present-simple",
      "sentenceForm": "affirmative"
    },
    {
      "imagem": "https://pub-1208463a3c774431bf7e0ddcbd3cf670.r2.dev/Niveis/118/001/000095.webp",
      "nomePortugues": "Carrinho de bebê",
      "nomeIngles": "Stroller",
      "categoria": "PlayTalk",
      "audio": "https://pub-1208463a3c774431bf7e0ddcbd3cf670.r2.dev/Niveis/118/001/000096.mp3",
      "tense": "present-simple",
      "sentenceForm": "affirmative"
    }
  ]
}
